fbonnardot/__init__.py
fbonnardot/cyclostationarity/__init__.py
fbonnardot/cyclostationarity/cyclicTimeCorr.py
fbonnardot/cyclostationarity/cycloTimeCorr.py
fbonnardot/cyclostationarity/syncAv.py
fbonnardot/detection/__init__.py
fbonnardot/detection/globalMinMax.py
fbonnardot/detection/peakDetection.py
fbonnardot/display/__init__.py
fbonnardot/display/periodPlot.py
fbonnardot/display/plotMatrix.py
fbonnardot/display/supPlot.py
fbonnardot/display/verticalLabel.py
fbonnardot/signalproc/__init__.py
fbonnardot/signalproc/circShift.py
fbonnardot/speed/__init__.py
fbonnardot/speed/demodAnalytic.py
fbonnardot/speed/synchronisation2.py
fbonnardot/various/__init__.py
fbonnardot/various/read_gpx.py
fbonnardot-2020.4.20.dist-info/METADATA
fbonnardot-2020.4.20.dist-info/WHEEL
fbonnardot-2020.4.20.dist-info/top_level.txt
fbonnardot-2020.4.20.dist-info/RECORD
