Metadata-Version: 2.1
Name: fbonnardot
Version: 2020.4.20
Summary: Signal processing tools for Python.
Home-page: https://github.com/fredujm/python_share
Author: Frédéric BONNARDOT
Author-email: frederic.bonnardot@univ-st-etienne.fr
License: GNU Affero General Public License v3 or later (AGPLv3+)
Platform: UNKNOWN
Classifier: Programming Language :: Python
Classifier: Development Status :: 1 - Planning
Classifier: Intended Audience :: Science/Research
Classifier: License :: OSI Approved :: GNU Affero General Public License v3 or later (AGPLv3+)
Classifier: Natural Language :: English
Classifier: Operating System :: OS Independent
Classifier: Programming Language :: Python :: 3 :: Only
Classifier: Topic :: Scientific/Engineering
Requires-Dist: numpy
Requires-Dist: scipy
Requires-Dist: matplotlib
Requires-Dist: PyQt5
